sia_code/__init__.py
sia_code/cli.py
sia_code/config.py
sia_code/core/__init__.py
sia_code/core/models.py
sia_code/core/types.py
sia_code/embed_server/__init__.py
sia_code/embed_server/client.py
sia_code/embed_server/daemon.py
sia_code/embed_server/protocol.py
sia_code/indexer/__init__.py
sia_code/indexer/chunk_index.py
sia_code/indexer/coordinator.py
sia_code/indexer/dependency_discovery.py
sia_code/indexer/doc_linker.py
sia_code/indexer/embedder.py
sia_code/indexer/hash_cache.py
sia_code/indexer/metrics.py
sia_code/indexer/project_analyzer.py
sia_code/memory/__init__.py
sia_code/memory/git_events.py
sia_code/memory/git_sync.py
sia_code/memory/summarizer.py
sia_code/parser/__init__.py
sia_code/parser/chunker.py
sia_code/parser/concepts.py
sia_code/parser/engine.py
sia_code/parser/languages/__init__.py
sia_code/search/__init__.py
sia_code/search/entity_extractor.py
sia_code/search/multi_hop.py
sia_code/search/query_preprocessor.py
sia_code/search/service.py
sia_code/search/single_hop.py
sia_code/storage/__init__.py
sia_code/storage/base.py
sia_code/storage/factory.py
sia_code/storage/usearch_backend.py
sia_code-0.5.0.dist-info/METADATA
sia_code-0.5.0.dist-info/WHEEL
sia_code-0.5.0.dist-info/entry_points.txt
sia_code-0.5.0.dist-info/top_level.txt
sia_code-0.5.0.dist-info/RECORD
