Metadata-Version: 2.4
Name: sia-code
Version: 0.5.0
Summary: Local-first codebase intelligence with semantic search, multi-hop research, and 12-language AST support
Author: Sia Code Contributors
License: MIT
Project-URL: Homepage, https://github.com/DxTa/sia-code
Project-URL: Documentation, https://github.com/DxTa/sia-code#readme
Project-URL: Repository, https://github.com/DxTa/sia-code
Project-URL: Issues, https://github.com/DxTa/sia-code/issues
Keywords: code-search,semantic-search,code-indexing,codebase-intelligence,tree-sitter,ast,code-analysis,developer-tools,cli
Classifier: Development Status :: 4 - Beta
Classifier: Environment :: Console
Classifier: Intended Audience :: Developers
Classifier: License :: OSI Approved :: MIT License
Classifier: Operating System :: OS Independent
Classifier: Programming Language :: Python :: 3
Classifier: Programming Language :: Python :: 3.10
Classifier: Programming Language :: Python :: 3.11
Classifier: Programming Language :: Python :: 3.12
Classifier: Topic :: Software Development
Classifier: Topic :: Software Development :: Documentation
Classifier: Topic :: Text Processing :: Indexing
Requires-Python: >=3.10
Requires-Dist: usearch>=2.0.0
Requires-Dist: sentence-transformers>=2.2
Requires-Dist: GitPython>=3.1.0
Requires-Dist: tree-sitter>=0.21.0
Requires-Dist: tree-sitter-python>=0.21.0
Requires-Dist: tree-sitter-javascript>=0.21.0
Requires-Dist: tree-sitter-typescript>=0.21.0
Requires-Dist: tree-sitter-go>=0.21.0
Requires-Dist: tree-sitter-rust>=0.21.0
Requires-Dist: tree-sitter-java>=0.21.0
Requires-Dist: tree-sitter-c>=0.21.0
Requires-Dist: tree-sitter-cpp>=0.21.0
Requires-Dist: tree-sitter-c-sharp>=0.21.0
Requires-Dist: tree-sitter-ruby>=0.21.0
Requires-Dist: tree-sitter-php>=0.21.0
Requires-Dist: click>=8.0
Requires-Dist: rich>=13.0
Requires-Dist: pathspec>=0.11
Requires-Dist: pydantic>=2.0
Requires-Dist: prompt-toolkit>=3.0
Requires-Dist: watchdog>=3.0
Requires-Dist: psutil>=5.9.0
Provides-Extra: openai
Requires-Dist: openai>=1.0; extra == "openai"
Provides-Extra: pdf
Requires-Dist: pypdf>=3.0; extra == "pdf"
Provides-Extra: all
Requires-Dist: openai>=1.0; extra == "all"
Requires-Dist: pypdf>=3.0; extra == "all"
Provides-Extra: dev
Requires-Dist: pytest>=7.0; extra == "dev"
Requires-Dist: pytest-cov>=4.0; extra == "dev"
Requires-Dist: pytest-timeout>=2.1; extra == "dev"
Requires-Dist: black>=23.0; extra == "dev"
Requires-Dist: ruff>=0.1.0; extra == "dev"
Requires-Dist: build>=1.0; extra == "dev"
Requires-Dist: twine>=4.0; extra == "dev"
Requires-Dist: bump-my-version>=0.20; extra == "dev"
Requires-Dist: anthropic>=0.30; extra == "dev"
Requires-Dist: google-generativeai>=0.5; extra == "dev"
